serial_usbipclient/__init__.py
serial_usbipclient/protocol/__init__.py
serial_usbipclient/protocol/packets.py
serial_usbipclient/protocol/urb_packets.py
serial_usbipclient/protocol/usb_descriptors.py
serial_usbipclient/protocol/usbip_defs.py
serial_usbipclient/protocol/usbip_protocol.py
serial_usbipclient/py.typed
serial_usbipclient/socket_wrapper.py
serial_usbipclient/usbip_client.py
serial_usbipclient/version.py
serial_usbipclient-1.1.2.dist-info/licenses/AUTHORS
serial_usbipclient-1.1.2.dist-info/licenses/LICENSE
serial_usbipclient-1.1.2.dist-info/METADATA
serial_usbipclient-1.1.2.dist-info/WHEEL
serial_usbipclient-1.1.2.dist-info/RECORD
