Metadata-Version: 2.4
Name: serial-usbipclient
Version: 1.1.2
Summary: Simple serial connectivity to CDC (serial) USB devices exposed by a USBIPD service.
License-File: AUTHORS
License-File: LICENSE
Keywords: usb,usbipd,serial
Author: Harry J. Collins
Author-email: bp100a@gmail.com
Maintainer: Harry J. Collins
Maintainer-email: bp100a@gmail.com
Requires-Python: >= 3.11
Classifier: Development Status :: 5 - Production/Stable
Classifier: Intended Audience :: Developers
Classifier: Topic :: System :: Hardware :: Universal Serial Bus (USB) :: Communications Device Class (CDC)
Classifier: License :: OSI Approved :: BSD License
Classifier: Operating System :: Microsoft :: Windows
Classifier: Operating System :: POSIX :: Linux
Classifier: Natural Language :: English
Classifier: Topic :: System :: Hardware :: Universal Serial Bus (USB) :: Communications Device Class (CDC)
Classifier: Programming Language :: Python :: Implementation :: CPython
Classifier: Programming Language :: Python
Classifier: Programming Language :: Python :: 3.11
Classifier: Programming Language :: Python :: 3.12
Classifier: Programming Language :: Python :: 3.13
Classifier: Programming Language :: Python :: 3.14
Requires-Dist: py-datastruct (>=1.1.0)
Requires-Dist: typing-extensions (>=4.15.0)
Project-URL: Repository, https://github.com/bp100a/serial-usbipclient
